sre_parse36.py
sre_parse36-1.0.0.dist-info/LICENSE
sre_parse36-1.0.0.dist-info/METADATA
sre_parse36-1.0.0.dist-info/WHEEL
sre_parse36-1.0.0.dist-info/top_level.txt
sre_parse36-1.0.0.dist-info/RECORD
