Metadata-Version: 2.1
Name: sre-parse36
Version: 1.0.0
Summary: Python 3.6 sre_parse module
Home-page: https://github.com/tristanlatr/sre_parse36
Author: Python Software Foundation
License: GNU General Public License v3.0
Platform: UNKNOWN
Classifier: Programming Language :: Python :: 3
